src/pyFAZ/__init__.py
src/pyFAZ/fmg.py
src/pyFMG/__init__.py
src/pyFMG/fmg.py
pyftntlib-0.1.0.dist-info/METADATA
pyftntlib-0.1.0.dist-info/WHEEL
pyftntlib-0.1.0.dist-info/top_level.txt
pyftntlib-0.1.0.dist-info/RECORD
