Metadata-Version: 2.4
Name: pyftntlib
Version: 0.1.0
Summary: A python package for all Fortinet products API.
Home-page: https://github.com/p4r4n0y1ng/pyfmg
Author: p4r4n0y1ng
Author-email: p4r4n0y1ng <jhuber@fortinet.com>, jpforcioli <jpforcioli@fortinet.com>
License-Expression: Apache-2.0
Project-URL: Homepage, https://github.com/jpforcioli/pyftntlib
Requires-Python: >=3.6
Requires-Dist: requests
Dynamic: author
Dynamic: home-page
